instarepo/__init__.py
instarepo/credentials.py
instarepo/git.py
instarepo/git_test.py
instarepo/github.py
instarepo/main.py
instarepo/main_test.py
instarepo/parsers.py
instarepo/parsers_test.py
instarepo/repo_source.py
instarepo/repo_source_test.py
instarepo/xml_utils.py
instarepo/commands/__init__.py
instarepo/commands/analyze.py
instarepo/commands/clone.py
instarepo/commands/fix.py
instarepo/commands/fix_test.py
instarepo/commands/list.py
instarepo/commands/login.py
instarepo/commands/logout.py
instarepo/fixers/__init__.py
instarepo/fixers/base.py
instarepo/fixers/changelog.py
instarepo/fixers/ci.py
instarepo/fixers/ci_test.py
instarepo/fixers/config.json
instarepo/fixers/config.py
instarepo/fixers/config.schema.json
instarepo/fixers/config_test.py
instarepo/fixers/context.py
instarepo/fixers/context_test.py
instarepo/fixers/discovery.py
instarepo/fixers/discovery_test.py
instarepo/fixers/dotnet.py
instarepo/fixers/dotnet_test.py
instarepo/fixers/finders.py
instarepo/fixers/finders_test.py
instarepo/fixers/license.py
instarepo/fixers/license_test.py
instarepo/fixers/maven.py
instarepo/fixers/maven_test.py
instarepo/fixers/maven_version_rules.xml
instarepo/fixers/missing_files.py
instarepo/fixers/missing_files_test.py
instarepo/fixers/naming.py
instarepo/fixers/naming_test.py
instarepo/fixers/pascal.py
instarepo/fixers/readme.py
instarepo/fixers/readme_test.py
instarepo/fixers/repo_description.py
instarepo/fixers/vb6.py
instarepo-0.14.0.dist-info/LICENSE
instarepo-0.14.0.dist-info/METADATA
instarepo-0.14.0.dist-info/WHEEL
instarepo-0.14.0.dist-info/entry_points.txt
instarepo-0.14.0.dist-info/top_level.txt
instarepo-0.14.0.dist-info/RECORD
