Metadata-Version: 2.1
Name: instarepo
Version: 0.14.0
Summary: CLI automation tool to batch process multiple repositories
Home-page: https://github.com/ngeor/instarepo
Author: Nikolaos Georgiou
Author-email: Nikolaos.Georgiou@gmail.com
License: UNKNOWN
Project-URL: Bug Tracker, https://github.com/ngeor/instarepo/issues
Platform: UNKNOWN
Classifier: Programming Language :: Python :: 3
Classifier: License :: OSI Approved :: MIT License
Classifier: Operating System :: OS Independent
Requires-Python: >=3.8
License-File: LICENSE
Requires-Dist: requests (==2.27.1)
